trax_extra_activation/__init__.py
trax_extra_activation/fns.py
trax_extra_activation-0.0.2.dist-info/WHEEL
trax_extra_activation-0.0.2.dist-info/METADATA
trax_extra_activation-0.0.2.dist-info/RECORD
