Metadata-Version: 2.1
Name: trax-extra-activation
Version: 0.0.2
Summary: Extra activation functions for Trax
Home-page: https://github.com/Catminusminus/trax-extra-activation
License: MIT
Keywords: trax,jax,machine learning
Author: Catminusminus
Author-email: getomya@svk.jp
Requires-Python: >=3.8,<4.0
Classifier: License :: OSI Approved :: MIT License
Classifier: Programming Language :: Python :: 3
Classifier: Programming Language :: Python :: 3.8
Classifier: Programming Language :: Python :: 3.9
Project-URL: Repository, https://github.com/Catminusminus/trax-extra-activation
